jschon/__init__.py
jschon/exc.py
jschon/exceptions.py
jschon/formats.py
jschon/json.py
jschon/jsonpatch.py
jschon/jsonpointer.py
jschon/jsonschema.py
jschon/output.py
jschon/py.typed
jschon/uri.py
jschon/utils.py
jschon/catalog/_2019_09.py
jschon/catalog/_2020_12.py
jschon/catalog/__init__.py
jschon/catalog/_next.py
jschon/catalog/json-schema-2019-09/hyper-schema.json
jschon/catalog/json-schema-2019-09/links.json
jschon/catalog/json-schema-2019-09/schema.json
jschon/catalog/json-schema-2019-09/meta/applicator.json
jschon/catalog/json-schema-2019-09/meta/content.json
jschon/catalog/json-schema-2019-09/meta/core.json
jschon/catalog/json-schema-2019-09/meta/format.json
jschon/catalog/json-schema-2019-09/meta/hyper-schema.json
jschon/catalog/json-schema-2019-09/meta/meta-data.json
jschon/catalog/json-schema-2019-09/meta/validation.json
jschon/catalog/json-schema-2019-09/output/hyper-schema.json
jschon/catalog/json-schema-2019-09/output/schema.json
jschon/catalog/json-schema-2019-09/output/verbose-example.json
jschon/catalog/json-schema-2020-12/hyper-schema.json
jschon/catalog/json-schema-2020-12/links.json
jschon/catalog/json-schema-2020-12/schema.json
jschon/catalog/json-schema-2020-12/archive/hyper-schema.json
jschon/catalog/json-schema-2020-12/archive/links.json
jschon/catalog/json-schema-2020-12/archive/meta/hyper-schema.json
jschon/catalog/json-schema-2020-12/meta/applicator.json
jschon/catalog/json-schema-2020-12/meta/content.json
jschon/catalog/json-schema-2020-12/meta/core.json
jschon/catalog/json-schema-2020-12/meta/format-annotation.json
jschon/catalog/json-schema-2020-12/meta/format-assertion.json
jschon/catalog/json-schema-2020-12/meta/hyper-schema.json
jschon/catalog/json-schema-2020-12/meta/meta-data.json
jschon/catalog/json-schema-2020-12/meta/unevaluated.json
jschon/catalog/json-schema-2020-12/meta/validation.json
jschon/catalog/json-schema-2020-12/output/hyper-schema.json
jschon/catalog/json-schema-2020-12/output/schema.json
jschon-0.11.1.dist-info/LICENSE
jschon-0.11.1.dist-info/METADATA
jschon-0.11.1.dist-info/WHEEL
jschon-0.11.1.dist-info/top_level.txt
jschon-0.11.1.dist-info/RECORD
