Metadata-Version: 2.1
Name: jschon
Version: 0.11.1
Summary: A JSON toolkit for Python developers.
Home-page: https://github.com/marksparkza/jschon
Author: Mark Jacobson
Author-email: mark@saeon.ac.za
License: MIT
Classifier: Development Status :: 3 - Alpha
Classifier: Intended Audience :: Developers
Classifier: License :: OSI Approved :: MIT License
Classifier: Operating System :: OS Independent
Classifier: Programming Language :: Python
Classifier: Programming Language :: Python :: 3
Classifier: Programming Language :: Python :: 3 :: Only
Classifier: Programming Language :: Python :: 3.8
Classifier: Programming Language :: Python :: 3.9
Classifier: Programming Language :: Python :: 3.10
Classifier: Programming Language :: Python :: 3.11
Classifier: Topic :: Software Development :: Libraries
Classifier: Topic :: Software Development :: Libraries :: Python Modules
Requires-Python: ~=3.8
License-File: LICENSE
Requires-Dist: rfc3986
Provides-Extra: requests
Requires-Dist: requests; extra == "requests"
Provides-Extra: test
Requires-Dist: tox; extra == "test"
Provides-Extra: dev
Requires-Dist: pytest; extra == "dev"
Requires-Dist: coverage; extra == "dev"
Requires-Dist: hypothesis<6.0.4; extra == "dev"
Requires-Dist: pytest-benchmark; extra == "dev"
Requires-Dist: pytest-httpserver; extra == "dev"
Requires-Dist: requests; extra == "dev"
Provides-Extra: doc
Requires-Dist: sphinx; extra == "doc"
Requires-Dist: sphinx-rtd-theme; extra == "doc"
